multiplexer_8_3/src/multiplexer.sv
module multiplexer(
  input logic [7:0] in,
  input logic [2:0] sel,
  output logic out
);

  always_comb begin
    case(sel)
      3'b000: out = in[0];
      3'b001: out = in[1];
      3'b010: out = in[2];
      3'b011: out = in[3];
      3'b100: out = in[4];
      3'b101: out = in[5];
      3'b110: out = in[6];
      3'b111: out = in[7];
    endcase
  end

endmodule : multiplexer

multiplexer_8_3/tb/multiplexer_tb.sv
`include "../src/multiplexer.sv"

module multiplexer_tb;

  logic [7:0] in;
  logic [2:0] sel;
  logic out;

  multiplexer multiplexer(
    .in(in),
    .sel(sel),
    .out(out)
  );

  initial begin
    $dumpfile("multiplexer_tb.vcd");
    $dumpvars(0);
    #10;
    in = 8'b01010101;
    sel = 0;
    #10;
    sel = 1;
    #10;
    sel = 2;
    #10;
    sel = 3;
    #10;
    sel = 4;
    #10;
    sel = 5;
    #10;
    sel = 6;
    #10;
    sel = 7;
    #10;
  end

endmodule : multiplexer_tb

multiplexer_8_3/simulations/SIM__2022_06_04__22_37_02/multiplexer_tb.vcd
$date
	Sat Jun  4 19:37:03 2022
$end
$version
	Icarus Verilog
$end
$timescale
	1s
$end
$scope module multiplexer_tb $end
$var wire 1 ! out $end
$var reg 8 " in [7:0] $end
$var reg 3 # sel [2:0] $end
$scope module multiplexer $end
$var wire 8 $ in [7:0] $end
$var wire 3 % sel [2:0] $end
$var reg 1 ! out $end
$upscope $end
$upscope $end
$enddefinitions $end
$comment Show the parameter values. $end
$dumpall
$end
#0
$dumpvars
bx %
bx $
bx #
bx "
x!
$end
#10
1!
b0 #
b0 %
b1010101 "
b1010101 $
#20
0!
b1 #
b1 %
#30
1!
b10 #
b10 %
#40
0!
b11 #
b11 %
#50
1!
b100 #
b100 %
#60
0!
b101 #
b101 %
#70
1!
b110 #
b110 %
#80
0!
b111 #
b111 %
