demultiplexer_3_8/src/demultiplexer.sv
module demultiplexer(
  input logic in,
  input logic [2:0] sel,
  output logic [7:0] out
);

  always_comb begin
    out[0] = (in & ~sel[2] & ~sel[1] & ~sel[0]);
    out[1] = (in & ~sel[2] & ~sel[1] & sel[0]);
    out[2] = (in & ~sel[2] & sel[1] & ~sel[0]);
    out[3] = (in & ~sel[2] & sel[1] & sel[0]);
    out[4] = (in & sel[2] & ~sel[1] & ~sel[0]);
    out[5] = (in & sel[2] & ~sel[1] & sel[0]);
    out[6] = (in & sel[2] & sel[1] & ~sel[0]);
    out[7] = (in & sel[2] & sel[1] & sel[0]);
  end

endmodule : demultiplexer

demultiplexer_3_8/tb/demultiplexer_tb.sv
`include "../src/demultiplexer.sv"

module demultiplexer_tb;

  logic in;
  logic [2:0] sel;
  logic [7:0] out;

  demultiplexer demultiplexer(
    .sel(sel),
    .in(in),
    .out(out)
  );

  initial begin
    $dumpfile("demultiplexer_tb.vcd");
    $dumpvars(0);
    #10;
    in = 1;
    sel = 3'b000;
    #10;
    sel = 3'b001;
    #10;
    sel = 3'b010;
    #10;
    sel = 3'b011;
    #10;
    sel = 3'b100;
    #10;
    sel = 3'b101;
    #10;
    sel = 3'b110;
    #10;
    sel = 3'b111;
    #10;
  end

endmodule : demultiplexer_tb

demultiplexer_3_8/simulations/SIM__2022_06_04__22_36_33/demultiplexer_tb.vcd
$date
	Sat Jun  4 19:36:33 2022
$end
$version
	Icarus Verilog
$end
$timescale
	1s
$end
$scope module demultiplexer_tb $end
$var wire 8 ! out [7:0] $end
$var reg 1 " in $end
$var reg 3 # sel [2:0] $end
$scope module demultiplexer $end
$var wire 1 " in $end
$var wire 3 $ sel [2:0] $end
$var reg 8 % out [7:0] $end
$upscope $end
$upscope $end
$enddefinitions $end
$comment Show the parameter values. $end
$dumpall
$end
#0
$dumpvars
bx %
bx $
bx #
x"
bx !
$end
#10
b1 !
b1 %
b0 #
b0 $
1"
#20
b10 !
b10 %
b1 #
b1 $
#30
b100 !
b100 %
b10 #
b10 $
#40
b1000 !
b1000 %
b11 #
b11 $
#50
b10000 !
b10000 %
b100 #
b100 $
#60
b100000 !
b100000 %
b101 #
b101 $
#70
b1000000 !
b1000000 %
b110 #
b110 $
#80
b10000000 !
b10000000 %
b111 #
b111 $
